tabular_export/__init__.py
tabular_export/admin.py
tabular_export/core.py
tabular_export/models.py
django4_tabular_export-1.0.1.dist-info/AUTHORS.rst
django4_tabular_export-1.0.1.dist-info/LICENSE
django4_tabular_export-1.0.1.dist-info/METADATA
django4_tabular_export-1.0.1.dist-info/WHEEL
django4_tabular_export-1.0.1.dist-info/top_level.txt
django4_tabular_export-1.0.1.dist-info/RECORD
