Metadata-Version: 2.1
Name: django4-tabular-export
Version: 1.0.1
Summary: Simple spreadsheet exports for Django 4+
Home-page: https://github.com/francoborrelli/django4-tabular-export
Author: Franco Borrelli
Author-email: francoborrelli96@gmail.com
License: CC0
Classifier: Development Status :: 5 - Production/Stable
Classifier: Framework :: Django
Classifier: Framework :: Django :: 4.0
Classifier: Intended Audience :: Developers
Classifier: License :: CC0 1.0 Universal (CC0 1.0) Public Domain Dedication
Classifier: Natural Language :: English
Classifier: Programming Language :: Python :: 3.8
License-File: LICENSE
License-File: AUTHORS.rst
Requires-Dist: django
Requires-Dist: xlsxwriter
